visier/__init__.py
visier/sdk/__init__.py
visier/sdk/api/__init__.py
visier/sdk/api/data_in/__init__.py
visier/sdk/api/data_in/api_client.py
visier/sdk/api/data_in/api_response.py
visier/sdk/api/data_in/configuration.py
visier/sdk/api/data_in/exceptions.py
visier/sdk/api/data_in/py.typed
visier/sdk/api/data_in/rest.py
visier/sdk/api/data_in/api/__init__.py
visier/sdk/api/data_in/api/data_and_job_handling_api.py
visier/sdk/api/data_in/api/data_intake_api.py
visier/sdk/api/data_in/api/data_upload_api.py
visier/sdk/api/data_in/api/direct_data_intake_api.py
visier/sdk/api/data_in/models/__init__.py
visier/sdk/api/data_in/models/adp_auth_params_dto.py
visier/sdk/api/data_in/models/assign_connector_credential_request.py
visier/sdk/api/data_in/models/assign_connector_credentials_by_tenant_response_dto.py
visier/sdk/api/data_in/models/assign_connector_credentials_response_dto.py
visier/sdk/api/data_in/models/assign_connector_with_credentials_response_dto.py
visier/sdk/api/data_in/models/assigned_credential_info_response_dto.py
visier/sdk/api/data_in/models/bamboo_auth_params_dto.py
visier/sdk/api/data_in/models/basic_s3_auth_params_dto.py
visier/sdk/api/data_in/models/big_query_auth_params_dto.py
visier/sdk/api/data_in/models/big_query_service_account_params_dto.py
visier/sdk/api/data_in/models/cancel_job_batch_from_job_id_dto.py
visier/sdk/api/data_in/models/connector.py
visier/sdk/api/data_in/models/connector_info_response_dto.py
visier/sdk/api/data_in/models/consolidated_analytics_job_request_dto.py
visier/sdk/api/data_in/models/copy_s3_auth_params_dto.py
visier/sdk/api/data_in/models/credential_creation_api_response_dto.py
visier/sdk/api/data_in/models/data_categories_response_dto.py
visier/sdk/api/data_in/models/data_category_response_dto.py
visier/sdk/api/data_in/models/data_load_request.py
visier/sdk/api/data_in/models/data_load_request_model.py
visier/sdk/api/data_in/models/data_load_response.py
visier/sdk/api/data_in/models/data_provider_auth_information_dto.py
visier.sdk.api.data_in-22222222.99201.1456.dist-info/METADATA
visier.sdk.api.data_in-22222222.99201.1456.dist-info/WHEEL
visier.sdk.api.data_in-22222222.99201.1456.dist-info/top_level.txt
visier.sdk.api.data_in-22222222.99201.1456.dist-info/RECORD
